tweetsave-1.1.0.dist-info/metadata.json
tweetsave-1.1.0.dist-info/top_level.txt
tweetsave-1.1.0.dist-info/WHEEL
tweetsave-1.1.0.dist-info/entry_points.txt
tweetsave-1.1.0.dist-info/METADATA
tweetsave-1.1.0.dist-info/RECORD
tweetsave-1.1.0.dist-info/DESCRIPTION.rst
tweetsave/__init__.py
tweetsave/api.py
tweetsave/cli.py
