Metadata-Version: 2.0
Name: tweetsave
Version: 1.1.0
Summary: A Python3 library for https://tweetsave.com
Home-page: https://github.com/kakakaya/tweetsave-python
Author: kakakaya
Author-email: kakakaya@gmail.com
License: MIT
Platform: UNKNOWN
Classifier: Programming Language :: Python :: 3.4
Classifier: Programming Language :: Python :: 3.5
Classifier: Programming Language :: Python :: 3.6
Classifier: Programming Language :: Python :: 3 :: Only
Requires-Dist: requests
Requires-Dist: click
